{
  "bugs_and_issues": [],
  "recommendations": [
    "Все архитектурные и технические замечания успешно исправлены. Продолжайте следовать тем же высоким стандартам на следующих этапах разработки."
  ],
  "score": 99,
  "stage_name": "Этап 1. Слой данных и Этап 2. Навигация (После дебаггинга)",
  "summary": "Все замечания из предыдущего отчета ревьюера полностью и качественно устранены: добавлены индексы для оптимизации запросов к таблице requests, внедрен интерфейс TimeProvider для тестируемости времени, обеспечено принудительное обнуление ID при создании заявок, и обновлены конвертеры Room для корректного учета локальной таймзоны (ZoneId.systemDefault()). Код полностью соответствует промышленным стандартам."
}